tests/__init__.py
tests/test_forces_postcode.py
tests/test_parse_error.py
tests/test_postcode.py
tests/test_postcode_parser.py
tests/test_postcode_types_module.py
tests/test_special_case.py
tests/test_special_case_postcode.py
tests/test_standard_postcode.py
tests/test_standard_postcode_validator.py
tests/test_validation_error.py
tests/test_validation_fault.py
wintersdeep_postcode/__init__.py
wintersdeep_postcode/postcode.py
wintersdeep_postcode/postcode_parser.py
wintersdeep_postcode/exceptions/__init__.py
wintersdeep_postcode/exceptions/parse_error.py
wintersdeep_postcode/exceptions/postcode_error.py
wintersdeep_postcode/exceptions/validation_error.py
wintersdeep_postcode/exceptions/validation_fault.py
wintersdeep_postcode/postcode_types/__init__.py
wintersdeep_postcode/postcode_types/forces_postcode/__init__.py
wintersdeep_postcode/postcode_types/forces_postcode/forces_postcode.py
wintersdeep_postcode/postcode_types/special_case_postcode/__init__.py
wintersdeep_postcode/postcode_types/special_case_postcode/special_case.py
wintersdeep_postcode/postcode_types/special_case_postcode/special_case_postcode.py
wintersdeep_postcode/postcode_types/special_case_postcode/special_cases/girobank.json
wintersdeep_postcode/postcode_types/special_case_postcode/special_cases/stanta-old.json
wintersdeep_postcode/postcode_types/standard_postcode/__init__.py
wintersdeep_postcode/postcode_types/standard_postcode/standard_postcode.py
wintersdeep_postcode/postcode_types/standard_postcode/standard_postcode_validator.json
wintersdeep_postcode/postcode_types/standard_postcode/standard_postcode_validator.py
wintersdeep_postcode-1.0.0.dist-info/LICENSE
wintersdeep_postcode-1.0.0.dist-info/METADATA
wintersdeep_postcode-1.0.0.dist-info/WHEEL
wintersdeep_postcode-1.0.0.dist-info/top_level.txt
wintersdeep_postcode-1.0.0.dist-info/RECORD
