Metadata-Version: 2.1
Name: wintersdeep-postcode
Version: 1.0.0
Summary: Python3.6+ library for working with British postcodes.
Home-page: https://www.github.com/wintersdeep/wintersdeep_postcode
Author: WintersDeep
Author-email: admin@wintersdeep.com
License: UNKNOWN
Platform: UNKNOWN
Classifier: Development Status :: 5 - Production/Stable
Classifier: License :: OSI Approved :: MIT License
Classifier: Programming Language :: Python :: 3
Classifier: Operating System :: OS Independent
Requires-Python: >=3.6
